{
  "$schema": "http://json-schema.org/draft-04/schema#",
  "id": "https://raw.githubusercontent.com/washingtonpost/ans-schema/master/src/main/resources/schema/ans/v0_4/story-elements/text.json",
  "description": "A textual content element",
  "type": "object",
  "allOf": [
    {
      "$ref": "https://raw.githubusercontent.com/washingtonpost/ans-schema/master/src/main/resources/schema/ans/v0_4/story-elements/story-element.json"
    }, {
      "properties": {
        "type": {
          "enum": [ "text" ]
        },
        "text": {
          "description": "The text of the paragraph.",
          "type": "string"
        }
      },
      "required": [ "text" ]
    }
  ]
}
