{
    "$schema": "http://json-schema.org/draft-04/schema#",
    "id": "https://raw.githubusercontent.com/washingtonpost/ans-schema/master/src/main/resources/schema/ans/v0_3/image.json",
    "title": "An image.",
    "description": "Holds attributes of an ANS image component.",
    "type": "object",
    "allOf": [{
            "$ref": "media.json",
            "properties": {
                "subtitle": {
                    "description": "Subtitle for the image.",
                    "type": "string"
                },
                "caption": {
                    "description": "Caption for the image.",
                    "type": "string"
                },
                "url": {
                    "description": "URL for the image.",
                    "type": "string"
                },
                "width": {
                    "description": "Width for the image.",
                    "type": "integer"
                },
                "height": {
                    "description": "Height for the image.",
                    "type": "integer"
                }
            }
        }
    ]
}
